{
    "__comment_:schema:drawer": "Menu order. Reserve space for menu keys to set the order.",
    "schema": {
        "inherit": {
            "data": {
                "drawer": {
                    "menu": {
                        "session:": {
                            "main": {},
                            "user": {},
                            "theme": {},
                            "info": {}
                        },
                        "session:true": {
                            "main": {},
                            "user": {},
                            "theme": {},
                            "info": {}
                        }
                    }
                },
                "navbar": {
                    "menu": {
                        "session:": {
                            "signin": {},
                            "signup": {},
                            "language": {}
                        },
                        "session:true": {
                            "signoff": {},
                            "language": {}
                        }
                    }
                }
            }
        }
    }
}
